flake8_header_validator.py
flake8_header_validator-0.0.3.dist-info/LICENSE
flake8_header_validator-0.0.3.dist-info/METADATA
flake8_header_validator-0.0.3.dist-info/WHEEL
flake8_header_validator-0.0.3.dist-info/entry_points.txt
flake8_header_validator-0.0.3.dist-info/top_level.txt
flake8_header_validator-0.0.3.dist-info/RECORD
