Metadata-Version: 2.1
Name: flake8-header-validator
Version: 0.0.3
Summary: Check if python file contain copyright text
Home-page: https://github.com/Umaaz/flake8-copyright-validator
Author: Ben Donnelly
Author-email: b.w.donnelly1@gmail.com
License: MIT
Classifier: Framework :: Flake8
Classifier: Development Status :: 3 - Alpha
Classifier: Intended Audience :: Developers
Classifier: License :: OSI Approved :: MIT License
Classifier: Natural Language :: Russian
Classifier: Operating System :: OS Independent
Classifier: Programming Language :: Python :: 3.7
Classifier: Programming Language :: Python :: 3.8
Classifier: Programming Language :: Python :: 3.9
Classifier: Programming Language :: Python :: 3.10
Classifier: Topic :: Software Development
Requires-Python: >=3.7
License-File: LICENSE
Requires-Dist: setuptools
Requires-Dist: flake8
Requires-Dist: importlib-metadata
